README.md
setup.py
bin/beanstalk_cleaner
bin/get_live_environment
bin/pymaws
bin/pymawspath
pymacaron_aws.egg-info/PKG-INFO
pymacaron_aws.egg-info/SOURCES.txt
pymacaron_aws.egg-info/dependency_links.txt
pymacaron_aws.egg-info/not-zip-safe
pymacaron_aws.egg-info/requires.txt
pymacaron_aws.egg-info/top_level.txt
pymacaron_deploy_configs/Dockerrun.aws.json.template
pymacaron_deploy_configs/__init__.py
pymacaron_deploy_configs/autoscaling.config
pymacaron_deploy_configs/aws-secrets.config
pymacaron_deploy_configs/healthcheckurl.config
pymacaron_deploy_configs/logs.config
pymacaron_deploy_configs/notifications.config
pymacaron_deploy_configs/rolling-updates.config