Metadata-Version: 1.1
Name: pymacaron-aws
Version: 0.0.99
Summary: Deploy a PyMacaron microservice to Amazon aws/docker
Home-page: https://github.com/pymacaron/pymacaron-aws
Author: Erwan Lemonnier
Author-email: erwan@lemonnier.se
License: BSD
Platform: any
Classifier: Environment :: Web Environment
Classifier: Intended Audience :: Developers
Classifier: License :: OSI Approved :: BSD License
Classifier: Operating System :: OS Independent
Classifier: Programming Language :: Python
Classifier: Topic :: Internet :: WWW/HTTP :: Dynamic Content
Classifier: Topic :: Software Development :: Libraries :: Python Modules
